django_formfactory-0.2.0.dist-info/DESCRIPTION.rst
django_formfactory-0.2.0.dist-info/METADATA
django_formfactory-0.2.0.dist-info/RECORD
django_formfactory-0.2.0.dist-info/WHEEL
django_formfactory-0.2.0.dist-info/metadata.json
django_formfactory-0.2.0.dist-info/top_level.txt
formfactory/__init__.py
formfactory/actions.py
formfactory/admin.py
formfactory/clean_methods.py
formfactory/exceptions.py
formfactory/factory.py
formfactory/forms.py
formfactory/models.py
formfactory/urls.py
formfactory/utils.py
formfactory/validators.py
formfactory/views.py
formfactory/api/__init__.py
formfactory/migrations/0001_initial.py
formfactory/migrations/0002_move_fields_to_form.py
formfactory/migrations/0003_formfieldgroup_show_title.py
formfactory/migrations/0004_remove_form_post_to.py
formfactory/migrations/0005_added_enum_generic_relation.py
formfactory/migrations/0006_additional_validator_many_to_many.py
formfactory/migrations/0007_additional_validators_can_be_blank.py
formfactory/migrations/0008_custom_field_error_messages.py
formfactory/migrations/0009_form_enable_csrf.py
formfactory/migrations/0010_add_clean_methods_to_forms.py
formfactory/migrations/0011_form_field_label_length_change.py
formfactory/migrations/0012_auto_20170703_1030.py
formfactory/migrations/__init__.py
formfactory/templates/formfactory/form_detail.html
formfactory/templates/formfactory/wizard_detail.html
formfactory/templates/formfactory/inclusion_tags/form_detail.html
formfactory/templatetags/__init__.py
formfactory/templatetags/formfactory_tags.py
formfactory/tests/__init__.py
formfactory/tests/models.py
formfactory/tests/test_actions.py
formfactory/tests/test_admin.py
formfactory/tests/test_base.py
formfactory/tests/test_clean_methods.py
formfactory/tests/test_error_messages.py
formfactory/tests/test_factory.py
formfactory/tests/test_models.py
formfactory/tests/test_templatetags.py
formfactory/tests/test_utils.py
formfactory/tests/test_validators.py
formfactory/tests/test_views.py
formfactory/tests/urls.py
formfactory/tests/formfactoryapp/__init__.py
formfactory/tests/formfactoryapp/actions.py
formfactory/tests/formfactoryapp/clean_methods.py
formfactory/tests/formfactoryapp/validators.py
