Metadata-Version: 2.0
Name: django-formfactory
Version: 0.2.0
Summary: Dynamic django form builder.
Home-page: http://github.com/praekelt/django-formfactory
Author: Praekelt Consulting
Author-email: dev@praekelt.com
License: BSD
Platform: UNKNOWN
Classifier: Programming Language :: Python
Classifier: License :: OSI Approved :: BSD License
Classifier: Operating System :: OS Independent
Classifier: Framework :: Django
Classifier: Intended Audience :: Developers
Classifier: Topic :: Internet :: WWW/HTTP :: Dynamic Content
Requires-Dist: django
Requires-Dist: django-formtools
